basedrelativity/__init__.py
basedrelativity/constants.py
basedrelativity/forward.py
basedrelativity/inverse.py
basedrelativity/observer.py
basedrelativity-0.1.dist-info/LICENSE
basedrelativity-0.1.dist-info/METADATA
basedrelativity-0.1.dist-info/WHEEL
basedrelativity-0.1.dist-info/top_level.txt
basedrelativity-0.1.dist-info/RECORD
