Metadata-Version: 2.1
Name: basedrelativity
Version: 0.1
Summary: Solve relativity problems and actually get the right answer.
Home-page: http://github.com/basedphysics/basedrelativity
Author: basedphysics
Author-email: contact@basedphysics.com
License: MIT
Classifier: Programming Language :: Python :: 3
Classifier: License :: OSI Approved :: MIT License
Requires-Python: >=3.8
License-File: LICENSE
